main.py
jtf-1.1.15.dist-info/LICENSE
jtf-1.1.15.dist-info/METADATA
jtf-1.1.15.dist-info/WHEEL
jtf-1.1.15.dist-info/top_level.txt
jtf-1.1.15.dist-info/RECORD
