Metadata-Version: 2.1
Name: jtf
Version: 1.1.15
Summary: Utilities for interacting with .jtf files.
Author: Timothy Phillips
License: MIT License
Project-URL: Repository, https://github.com/NotTimTam/jtf.py
Project-URL: Issues, https://github.com/NotTimTam/jtf/issues
Keywords: json,table,spreadsheet,fileformat,utility
Classifier: Development Status :: 5 - Production/Stable
Classifier: Intended Audience :: Developers
Classifier: License :: OSI Approved :: MIT License
Classifier: Programming Language :: Python :: 3.12
Requires-Python: >=3.12
License-File: LICENSE
